urlcounter/__init__.py
urlcounter/urlcounter.py
urlcounter-0.0.3.dist-info/LICENSE
urlcounter-0.0.3.dist-info/METADATA
urlcounter-0.0.3.dist-info/WHEEL
urlcounter-0.0.3.dist-info/top_level.txt
urlcounter-0.0.3.dist-info/RECORD
