Metadata-Version: 2.1
Name: urlcounter
Version: 0.0.3
Summary: A set of functions that tally URLs within an event-based corpus. It assumes that you have data divided into a range of event-based periods with community-detected modules/hubs. It also assumes that you have unspooled and cleaned your URL data. See Deen Freelon's unspooler module for help: https://github.com/dfreelon/unspooler.
Home-page: https://github.com/lingeringcode/urlcounter/
Author: Chris A. Lindgren
Author-email: chris.a.lindgren@gmail.com
License: UNKNOWN
Download-URL: https://github.com/lingeringcode/urlcounter/
Keywords: data processing,summary analysis,URL,circulation studies
Platform: UNKNOWN
Requires-Dist: pandas
